pulumi_random/__init__.py
pulumi_random/_utilities.py
pulumi_random/provider.py
pulumi_random/pulumi-plugin.json
pulumi_random/py.typed
pulumi_random/random_bytes.py
pulumi_random/random_id.py
pulumi_random/random_integer.py
pulumi_random/random_password.py
pulumi_random/random_pet.py
pulumi_random/random_shuffle.py
pulumi_random/random_string.py
pulumi_random/random_uuid.py
pulumi_random-4.18.5.dist-info/METADATA
pulumi_random-4.18.5.dist-info/WHEEL
pulumi_random-4.18.5.dist-info/top_level.txt
pulumi_random-4.18.5.dist-info/RECORD
